lyrebird_tracking/__init__.py
lyrebird_tracking/context.py
lyrebird_tracking/tracking.py
lyrebird_tracking/webui.py
lyrebird_tracking/data/base.json
lyrebird_tracking/report_template/index.html
lyrebird_tracking/report_template/main.js
lyrebird_tracking/report_template/report.html
lyrebird_tracking/report_template/components/filter-tag.js
lyrebird_tracking/report_template/components/tracking-detail.js
lyrebird_tracking/report_template/data/report-data.js
lyrebird_tracking/report_template/style/report.css
lyrebird_tracking/server/__init__.py
lyrebird_tracking/server/base_handler.py
lyrebird_tracking/server/data_manager.py
lyrebird_tracking/server/search_handler.py
lyrebird_tracking/server/validator.py
lyrebird_tracking/static/component/banner.vue
lyrebird_tracking/static/component/filter-tag.vue
lyrebird_tracking/static/component/main.vue
lyrebird_tracking/static/component/tracking-detail.vue
lyrebird_tracking/static/component/tracking-list.vue
lyrebird_tracking/static/js/main.js
lyrebird_tracking/templates/index.html
lyrebird_tracking-0.10.1.dist-info/METADATA
lyrebird_tracking-0.10.1.dist-info/WHEEL
lyrebird_tracking-0.10.1.dist-info/entry_points.txt
lyrebird_tracking-0.10.1.dist-info/top_level.txt
lyrebird_tracking-0.10.1.dist-info/RECORD
