Metadata-Version: 2.1
Name: lyrebird-tracking
Version: 0.10.1
Summary: UNKNOWN
Home-page: https://github.com/meituan/lyrebird-tracking
Author: HBQA
License: UNKNOWN
Platform: UNKNOWN
Classifier: Programming Language :: Python :: 3 :: Only
Classifier: Programming Language :: Python :: 3.6
Classifier: License :: OSI Approved :: MIT License
Classifier: Operating System :: MacOS
Requires-Dist: lyrebird
Requires-Dist: jsonschema
